README.md
setup.py
glistener.egg-info/PKG-INFO
glistener.egg-info/SOURCES.txt
glistener.egg-info/dependency_links.txt
glistener.egg-info/entry_points.txt
glistener.egg-info/top_level.txt
listener/__init__.py
listener/gpu_standalone_listener.py