Metadata-Version: 1.0
Name: glistener
Version: 1.0.0
Summary: single gpu listener of one time period
Home-page: https://github.com/leefyi/gpu_listener
Author: leefyi
Author-email: leefyi@126.com
License: MIT License
Platform: UNKNOWN
